feature_engineering/__init__.py
feature_engineering/feature_engineer.py
feature_engineering/feature_importance_evaluator.py
feature_engineering/feature_selector.py
feature_engineering_5632425-0.1.1.dist-info/METADATA
feature_engineering_5632425-0.1.1.dist-info/WHEEL
feature_engineering_5632425-0.1.1.dist-info/entry_points.txt
feature_engineering_5632425-0.1.1.dist-info/RECORD
