Metadata-Version: 2.4
Name: feature_engineering_5632425
Version: 0.1.1
Summary: Feature extraction and validation schema tools
Author: Katsiaryna
Author-email: katsiaryna.shymchonak@innowise.com
Requires-Python: >=3.12
Classifier: Programming Language :: Python :: 3
Classifier: Programming Language :: Python :: 3.12
Classifier: Programming Language :: Python :: 3.13
Classifier: Programming Language :: Python :: 3.14
Requires-Dist: dill
Requires-Dist: numpy
Requires-Dist: pandas
Requires-Dist: scikit-learn
Requires-Dist: shap
